smfucker/__init__.py
smfucker/smfucker.py
smfucker/smms.py
smfucker-1.0.5.dist-info/License
smfucker-1.0.5.dist-info/METADATA
smfucker-1.0.5.dist-info/WHEEL
smfucker-1.0.5.dist-info/entry_points.txt
smfucker-1.0.5.dist-info/top_level.txt
smfucker-1.0.5.dist-info/RECORD
