Metadata-Version: 2.1
Name: smfucker
Version: 1.0.5
Summary: UNKNOWN
Home-page: https://github.com/The-Itach1//smfucker
Author: The_Itach1
Author-email: 2507709326@qq.com
License: UNKNOWN
Platform: UNKNOWN
Classifier: Programming Language :: Python :: 3
Classifier: License :: OSI Approved :: MIT License
Classifier: Operating System :: OS Independent
Requires-Python: >=3
Requires-Dist: requests
